covey/CoveyLedger.json
covey/__init__.py
covey/accountGenerator.js
covey/covey_calendar.py
covey/covey_checks.py
covey/covey_portfolio.py
covey/covey_pricer.py
covey/covey_trade.py
covey/utils.py
covey/workspace.code-workspace
covey/__pycache__/__init__.cpython-37.pyc
covey/__pycache__/covey_calendar.cpython-310.pyc
covey/__pycache__/covey_calendar.cpython-37.pyc
covey/__pycache__/covey_checks.cpython-310.pyc
covey/__pycache__/covey_checks.cpython-37.pyc
covey/__pycache__/covey_portfolio.cpython-37.pyc
covey/__pycache__/covey_price.cpython-310.pyc
covey/__pycache__/covey_pricer.cpython-310.pyc
covey/__pycache__/covey_pricer.cpython-37.pyc
covey/__pycache__/covey_trade.cpython-310.pyc
covey/__pycache__/covey_trade.cpython-37.pyc
covey/__pycache__/portfolio.cpython-310.pyc
covey/__pycache__/price.cpython-310.pyc
covey/__pycache__/utils.cpython-310.pyc
covey/__pycache__/utils.cpython-37.pyc
covey/checks/unpriced_crypto_0x55E580d9e296f9Ef7F02fe1516A0925629726801.csv
covey/checks/unpriced_crypto_0xd019955e5Db68ebd41CE5A7A327DdD5f2658e8D9.csv
covey/checks/unpriced_crypto_test_0x594F56D21ad544F6B567F3A49DB0F9a7B501FF37.csv
covey/data/allWallets.csv
covey/data/dividend_split.csv
covey/data/mergers.csv
covey/data/most_active_wallets.csv
covey/data/polygon_prior_to_20230301.csv
covey/data/ticker_changes.csv
covey/output/latest_positions.csv
covey/output/portfolio.csv
covey/output/price_key.csv
covey/output/trading_key.csv
covey_sdk-0.1.16.dist-info/LICENSE
covey_sdk-0.1.16.dist-info/METADATA
covey_sdk-0.1.16.dist-info/WHEEL
covey_sdk-0.1.16.dist-info/top_level.txt
covey_sdk-0.1.16.dist-info/RECORD
