Metadata-Version: 2.1
Name: covey-sdk
Version: 0.1.16
Summary: Covey Trading Tools
Home-page: https://github.com/covey-io/ethereum-contract-interaction
Author: Vadim Serebrinskiy
Author-email: vs@covey.io
License: MIT
Keywords: covey
Platform: UNKNOWN
License-File: LICENSE
Requires-Dist: alpaca-py (==0.8.2)
Requires-Dist: eth-account (==0.6.1)
Requires-Dist: eth-keys (==0.4.0)
Requires-Dist: pandas (==1.3.5)
Requires-Dist: python-dotenv (==0.20.0)
Requires-Dist: pytz (==2022.1)
Requires-Dist: web3 (==6.0.0b3)
